sms_message_aws_local_python_package/SendAwsSms.py
sms_message_aws_local_python_package/__init__.py
sms_message_aws_local_python_package-0.0.1.dist-info/METADATA
sms_message_aws_local_python_package-0.0.1.dist-info/WHEEL
sms_message_aws_local_python_package-0.0.1.dist-info/top_level.txt
sms_message_aws_local_python_package-0.0.1.dist-info/RECORD
