Metadata-Version: 2.1
Name: sms-message-aws-local-python-package
Version: 0.0.1
Summary: PyPI Package for Circles AWS sms
Home-page: https://github.com/circ-zone/sms-message-aws-local-python-package.git
Author: Circles
Author-email: info@circlez.ai
Classifier: Programming Language :: Python :: 3
Classifier: License :: Other/Proprietary License
Classifier: Operating System :: OS Independent
